odoo/addons/stock_storage_category_capacity_name/README.rst
odoo/addons/stock_storage_category_capacity_name/__init__.py
odoo/addons/stock_storage_category_capacity_name/__manifest__.py
odoo/addons/stock_storage_category_capacity_name/i18n/it.po
odoo/addons/stock_storage_category_capacity_name/i18n/stock_storage_category_capacity_name.pot
odoo/addons/stock_storage_category_capacity_name/models/__init__.py
odoo/addons/stock_storage_category_capacity_name/models/stock_storage_category_capacity.py
odoo/addons/stock_storage_category_capacity_name/readme/CONTRIBUTORS.md
odoo/addons/stock_storage_category_capacity_name/readme/DESCRIPTION.md
odoo/addons/stock_storage_category_capacity_name/static/description/icon.png
odoo/addons/stock_storage_category_capacity_name/static/description/index.html
odoo/addons/stock_storage_category_capacity_name/tests/__init__.py
odoo/addons/stock_storage_category_capacity_name/tests/test_capacity_name.py
odoo_addon_stock_storage_category_capacity_name-18.0.1.0.1.dist-info/METADATA
odoo_addon_stock_storage_category_capacity_name-18.0.1.0.1.dist-info/WHEEL
odoo_addon_stock_storage_category_capacity_name-18.0.1.0.1.dist-info/top_level.txt
odoo_addon_stock_storage_category_capacity_name-18.0.1.0.1.dist-info/RECORD
