Metadata-Version: 2.1
Name: odoo-addon-stock_storage_category_capacity_name
Version: 18.0.1.0.1
Requires-Python: >=3.10
Requires-Dist: odoo==18.0.*
Summary: Allows to have a better display name for Stock Storage Category Capacity model
Home-page: https://github.com/OCA/stock-logistics-warehouse
License: AGPL-3
Author: ACSONE SA/NV,Odoo Community Association (OCA)
Author-email: support@odoo-community.org
Classifier: Programming Language :: Python
Classifier: Framework :: Odoo
Classifier: Framework :: Odoo :: 18.0
Classifier: License :: OSI Approved :: GNU Affero General Public License v3
